{"locations":[{"_id":"5aa086cbd544c00004109147","country":"US","city":"Mobile"},{"_id":"5aa0913ac72ea20004028d0e","country":"US","city":"New York"},{"_id":"5aa091d1c72ea20004028d0f","country":"UK","city":"London"},{"_id":"5aa091dbc72ea20004028d10","country":"US","city":"Los Angeles"},{"_id":"5aa0935bc72ea20004028d13","country":"US","city":"Seattle"},{"_id":"5aa0954dc72ea20004028d1a","country":"DE","city":"Berlin"},{"_id":"5aa0963cc72ea20004028d1c","country":"US","city":"Denver"},{"_id":"5aa09902c72ea20004028d1f","country":"CA","city":"Halifax"},{"_id":"5aa099d4c72ea20004028d21","country":"UK","city":"Brighton"},{"_id":"5aa09cc4c72ea20004028d26","country":"SE","city":"Stockholm"},{"_id":"5aa09d70c72ea20004028d28","country":"US","city":"Baltimore"},{"_id":"5aa09f78c72ea20004028d2b","country":"NL","city":"Amsterdam"},{"_id":"5aa0a198c72ea20004028d30","country":"US","city":"San Jose"},{"_id":"5aa0a414c72ea20004028d34","country":"FR","city":"Paris"},{"_id":"5aa0a529c72ea20004028d37","country":"FR","city":"Nice"},{"_id":"5aa0a6b8c72ea20004028d3a","country":"US","city":"Washington DC"},{"_id":"5aa0a764c72ea20004028d3d","country":"SE","city":"Gothenburg"},{"_id":"5aa0a99bc72ea20004028d42","country":"CA","city":"Toronto"},{"_id":"5aa0ac2ac72ea20004028d48","country":"ES","city":"Barcelona"},{"_id":"5aa0aecdc72ea20004028d4c","country":"CA","city":"Montreal"},{"_id":"5aa0b0dcc72ea20004028d51","country":"MX","city":"Guadalajara"},{"_id":"5aa0b182c72ea20004028d53","country":"SG","city":"Singapore"},{"_id":"5aa0b252c72ea20004028d57","country":"US","city":"Atlanta"},{"_id":"5aa0b468c72ea20004028d5b","country":"AT","city":"Vienna"},{"_id":"5aa0b49ec72ea20004028d5c","country":"UK","city":"Derby"},{"_id":"5aa0b611c72ea20004028d60","country":"UK","city":"Edinburgh"},{"_id":"5aa0b776c72ea20004028d64","country":"IT","city":"Rome"},{"_id":"5aa0b95fc72ea20004028d69","country":"US","city":"Boston"},{"_id":"5aa0bbbcc72ea20004028d70","country":"IS","city":"Reykjavik"},{"_id":"5aa0bfc1c72ea20004028d76","country":"US","city":"Brooklyn"},{"_id":"5aa0c050c72ea20004028d78","country":"US","city":"Dallas"},{"_id":"5aa58b00b04ec100048efd9b","country":"US","city":"Troy"},{"_id":"5aa59223b04ec100048efda4","country":"US","city":"Chicago"},{"_id":"5aa59788c2f5310004ca05b7","country":"PT","city":"Porto"},{"_id":"5aa599dfc2f5310004ca05bc","country":"CA","city":"Calgary"},{"_id":"5aa59b7bc2f5310004ca05be","country":"BR","city":"Belo Horizonte"},{"_id":"5aa59c0fc2f5310004ca05c0","country":"UK","city":"Manchester"},{"_id":"5aa702f1233f4e0004c0c515","country":"CH","city":"Lausanne"},{"_id":"5aa70360233f4e0004c0c516","country":"US","city":"Phoenix"},{"_id":"5aa70778233f4e0004c0c51d","country":"DK","city":"Copenhagen"},{"_id":"5aa70869233f4e0004c0c521","country":"BR","city":"Barueri"},{"_id":"5aa708fe233f4e0004c0c525","country":"IN","city":"Mumbai"},{"_id":"5aa70a08233f4e0004c0c527","country":"UK","city":"Norwich"},{"_id":"5aa70a96233f4e0004c0c529","country":"AU","city":"Melbourne"},{"_id":"5aa70b89233f4e0004c0c52c","country":"AU","city":"Sydney"},{"_id":"5aa70c30233f4e0004c0c52e","country":"MX","city":"Mexico City"},{"_id":"5aa70cbe233f4e0004c0c530","country":"AU","city":"Adelaide"},{"_id":"5aa70d3d233f4e0004c0c532","country":"US","city":"Madison"},{"_id":"5aa70e30233f4e0004c0c535","country":"ES","city":"Madrid"},{"_id":"5aa70f76233f4e0004c0c538","country":"US","city":"St. Paul"},{"_id":"5aa71268233f4e0004c0c53d","country":"ZA","city":"Cape Town"},{"_id":"5aa82c2b829b1f00040a9cba","country":"US","city":"Bend"},{"_id":"5aa82db7829b1f00040a9cbd","country":"US","city":"Portland"},{"_id":"5aa82f4b829b1f00040a9cc2","country":"CO","city":"Bogota"},{"_id":"5aa831d1829b1f00040a9cc4","country":"AR","city":"Buenos Aires"},{"_id":"5aa8330f829b1f00040a9cca","country":"US","city":"Norwalk"},{"_id":"5aa8340b829b1f00040a9ccc","country":"IT","city":"Modena"},{"_id":"5aa83499829b1f00040a9cce","country":"CA","city":"Vancouver"},{"_id":"5aa8352e829b1f00040a9cd0","country":"US","city":"San Francisco"},{"_id":"5aa83d6e829b1f00040a9ce5","country":"US","city":"Savannah"},{"_id":"5aa8582d829b1f00040a9ce8","country":"AR","city":"Tandil"},{"_id":"5aa8593c829b1f00040a9ce9","country":"SA","city":"Jeddah"},{"_id":"5ab04314f67eac00045f1586","country":"US","city":"Columbus"},{"_id":"5ab047f6f67eac00045f158f","country":"IN","city":"New Delhi"},{"_id":"5ab0491cf67eac00045f1593","country":"DE","city":"Frankfurt"},{"_id":"5ab051e4f67eac00045f159f","country":"US","city":"Sacramento"},{"_id":"5ab052cef67eac00045f15a1","country":"AU","city":"Cairns"},{"_id":"5ab053c9f67eac00045f15a4","country":"UK","city":"Glasgow"},{"_id":"5ab054faf67eac00045f15a7","country":"US","city":"Salt Lake City"},{"_id":"5ab05581f67eac00045f15a9","country":"IE","city":"Dublin"},{"_id":"5ab1302efc5d29000496ce98","country":"US","city":"Burbank"},{"_id":"5ab13132fc5d29000496ce9c","country":"CA","city":"London"},{"_id":"5ab131e3fc5d29000496ce9d","country":"BR","city":"João Pessoa"},{"_id":"5ab13500fc5d29000496cea2","country":"US","city":"Houston"},{"_id":"5ab1369cfc5d29000496cea7","country":"PT","city":"Lisbon"},{"_id":"5ab6aa7a4a97c1000456bfd7","country":"US","city":"Doylestown"},{"_id":"5ab6ab574a97c1000456bfd9","country":"UY","city":"El Pinar"},{"_id":"5ab6ac484a97c1000456bfdc","country":"US","city":"Ridgefield"},{"_id":"5ab6acbe4a97c1000456bfde","country":"US","city":"New Orleans"},{"_id":"5abe4ede65364700049d3dca","country":"DE","city":"Bremen"},{"_id":"5abe4f9365364700049d3dcc","country":"US","city":"Boulder"},{"_id":"5abe50a265364700049d3dcf","country":"UK","city":"Leeds"},{"_id":"5abe523665364700049d3dd3","country":"US","city":"Austin"},{"_id":"5abe542765364700049d3dd6","country":"AU","city":"Brisbane"},{"_id":"5abe549065364700049d3dd8","country":"IT","city":"Milan"},{"_id":"5abe553065364700049d3ddb","country":"US","city":"Minneapolis"},{"_id":"5abe565765364700049d3ddc","country":"US","city":"Alexandria"},{"_id":"5ac7a50a3a7a510004e2d247","country":"US","city":"Jersey City"},{"_id":"5ac7a8473a7a510004e2d24d","country":"KR","city":"Seoul"},{"_id":"5ac7b9b33a7a510004e2d257","country":"CH","city":"Zurich"},{"_id":"5ac7ba2b3a7a510004e2d259","country":"UA","city":"Lviv"},{"_id":"5ac7bb2a3a7a510004e2d25e","country":"US","city":"Sarasota"},{"_id":"5ac926009617f2000478d23e","country":"US","city":"Fort Worth"},{"_id":"5ac92b869617f2000478d246","country":"SE","city":"Malmö"},{"_id":"5ac92c569617f2000478d248","country":"IT","city":"Reggio nell Emilia"},{"_id":"5ac92d069617f2000478d24b","country":"US","city":"Providence"},{"_id":"5ac92e4b9617f2000478d250","country":"UK","city":"Epsom"},{"_id":"5ac93bbe9617f2000478d25a","country":"DE","city":"Munich"},{"_id":"5ac940a89617f2000478d265","country":"US","city":"Milwaukee"},{"_id":"5ac941e29617f2000478d269","country":"NL","city":"Eindhoven"},{"_id":"5ac944019617f2000478d26d","country":"US","city":"New Milford"},{"_id":"5ac9453f9617f2000478d271","country":"BE","city":"Gent"},{"_id":"5ac9468d9617f2000478d275","country":"UK","city":"Chichester"},{"_id":"5ad87c0d5863d000045fe12d","country":"US","city":"Stamford"},{"_id":"5ad87e6a5863d000045fe133","country":"US","city":"Louisville"},{"_id":"5ad880ea5863d000045fe13a","country":"BR","city":"Recife"},{"_id":"5ad881b75863d000045fe13d","country":"IT","city":"Bergamo"},{"_id":"5ad8826e5863d000045fe140","country":"US","city":"Fort Lauderdale"},{"_id":"5ad882e85863d000045fe142","country":"US","city":"Richmond"},{"_id":"5ad89baa5863d000045fe146","country":"RU","city":"Saint Petersburg"},{"_id":"5ad89c385863d000045fe148","country":"PH","city":"Pili"},{"_id":"5ad89d4e5863d000045fe14d","country":"US","city":"Detroit"},{"_id":"5ad89dd75863d000045fe14e","country":"BR","city":"São Paulo"},{"_id":"5ad89e375863d000045fe150","country":"US","city":"Ann Arbor"},{"_id":"5ad89e945863d000045fe152","country":"AU","city":"Wagga Wagga"},{"_id":"5ad89f9c5863d000045fe156","country":"US","city":"Saint Louis"},{"_id":"5ad9bbd370a7300004b72d3b","country":"US","city":"Mountain View"},{"_id":"5ad9bc5870a7300004b72d3e","country":"IT","city":"Verona"},{"_id":"5ad9be2670a7300004b72d41","country":"IL","city":"Tel Aviv"},{"_id":"5ad9c05870a7300004b72d46","country":"US","city":"Santa Monica"},{"_id":"5ad9c0fa70a7300004b72d48","country":"BR","city":"Rio de Janeiro"},{"_id":"5ad9c34670a7300004b72d4f","country":"BR","city":"Bauru"},{"_id":"5ae5f8b328dd7600043f47d5","country":"US","city":"Peoria"},{"_id":"5af7086b9342bc0004a66c4f","country":"DE","city":"Leipzig"},{"_id":"5af70c579342bc0004a66c53","country":"US","city":"Oakland"},{"_id":"5af710259342bc0004a66c56","country":"US","city":"Rochester"},{"_id":"5afdf23ee5ad2100049ea00e","country":"US","city":"Charlottesville"},{"_id":"5afdf350e5ad2100049ea010","country":"US","city":"Queens"},{"_id":"5afdf740e5ad2100049ea019","country":"US","city":"San Diego"},{"_id":"5b0443a0fcdd8d0004af27f3","country":"DK","city":"Viborg"},{"_id":"5b0444a8fcdd8d0004af27f6","country":"UK","city":"Belfast"},{"_id":"5b170fc9e94fc100045bc43e","country":"US","city":"Marietta"},{"_id":"5b171321e94fc100045bc443","country":"UA","city":"Kiev"},{"_id":"5b1715cde94fc100045bc447","country":"CN","city":"Shanghai"},{"_id":"5b171625e94fc100045bc449","country":"CN","city":"Beijing"},{"_id":"5b1717c5e94fc100045bc44d","country":"UA","city":"Ivano-Frankivsk"},{"_id":"5b1719d3e94fc100045bc451","country":"US","city":"Santa Barbara"},{"_id":"5b171d4ce94fc100045bc45a","country":"US","city":"St. Louis"},{"_id":"5b171e90e94fc100045bc45e","country":"ES","city":"Valencia"},{"_id":"5b297e8038ec890004490ad7","country":"DE","city":"Cologne"},{"_id":"5b3a7f34c604e80004a93aaa","country":"US","city":"Hartford"},{"_id":"5b3a89eac604e80004a93ab4","country":"US","city":"Beverly Hills"},{"_id":"5b3a8a43c604e80004a93ab5","country":"IR","city":"Tehran"},{"_id":"5b60c896a7decd0004097e9e","country":"US","city":"Philadelphia"},{"_id":"5b60d059a7decd0004097ead","country":"US","city":"Kansas City"},{"_id":"5b60d10ba7decd0004097eb0","country":"US","city":"Colorado Springs"},{"_id":"5b786fcb5b0c12000424ac64","country":"US","city":"Manassas"},{"_id":"5b7871595b0c12000424ac68","country":"DK","city":"Aarhus"},{"_id":"5b7872235b0c12000424ac69","country":"PL","city":"Kraków"},{"_id":"5b7dc6136dbc4a0004e3ba76","country":"US","city":"Glendale"},{"_id":"5b7dc7c26dbc4a0004e3ba7a","country":"CL","city":"Santiago"},{"_id":"5b9fc0c456cc0100040cf7e9","country":"US","city":"Chandler"},{"_id":"5b9fc45956cc0100040cf7f0","country":"CH","city":"Geneva"},{"_id":"5b9fc7ce56cc0100040cf7f6","country":"PR","city":"San Juan"},{"_id":"5bb2b75c3a25360004d93812","country":"UK","city":"Winchester"},{"_id":"5bb34de5a09c850004ec097e","country":"GT","city":"Guatemala City"},{"_id":"5bd24f83bf539e000430fe66","country":"UK","city":"Bristol"},{"_id":"5bd25dedbf539e000430fe73","country":"BR","city":"Campinas"},{"_id":"5bdf68d0f1848600044cbeaf","country":"ES","city":"Pamplona"},{"_id":"5bdf6a31f1848600044cbeb3","country":"CS","city":"Kula"},{"_id":"5c092fbd0f65510004459833","country":"NO","city":"Oslo"},{"_id":"5c09321c0f6551000445983a","country":"FR","city":"Bayonne"},{"_id":"5c0933b40f6551000445983e","country":"TR","city":"Istanbul"},{"_id":"5c0935360f65510004459842","country":"US","city":"Mechanicsville"},{"_id":"5c320f7be299ca0004175131","country":"FR","city":"Château Arnoux Saint Auban "},{"_id":"5c321093e299ca0004175134","country":"MX","city":"Hermosillo"},{"_id":"5c321132e299ca0004175136","country":"US","city":"Berkeley"},{"_id":"5c321270e299ca0004175137","country":"SV","city":"San Salvador"},{"_id":"5c3213b8e299ca000417513c","country":"US","city":"Miami"},{"_id":"5c32144ee299ca000417513e","country":"SI","city":"Ljubljana"},{"_id":"5c3214efe299ca0004175140","country":"IE","city":"Meath"},{"_id":"5c5d7c6b1c32f10004008237","country":"MD","city":"Chinisau"},{"_id":"5c7d6375f3ae0c0004df4b9c","country":"US","city":"Sherman"},{"_id":"5c7d653df3ae0c0004df4ba0","country":"US","city":"Cleveland"},{"_id":"5c7d664cf3ae0c0004df4ba3","country":"GR","city":"Athens"},{"_id":"5c7d6747f3ae0c0004df4ba6","country":"US","city":"Vernon"},{"_id":"5c7d6e28f3ae0c0004df4bb2","country":"PH","city":"Cagayan de Oro"},{"_id":"5ca390df2c7b9d0004d930d1","country":"US","city":"Orlando"},{"_id":"5ca392c52c7b9d0004d930d5","country":"UK","city":"Nottingham"},{"_id":"5ca3c9442c7b9d0004d930e8","country":"FR","city":"Lyon"},{"_id":"5ca3c9d32c7b9d0004d930ea","country":"US","city":"Lexington"},{"_id":"5ca3cae92c7b9d0004d930ed","country":"US","city":"Charlotte"},{"_id":"5ce15b55a89ea100045373ae","country":"US","city":"Port Townsend"},{"_id":"5ce15c5ea89ea100045373b0","country":"UK","city":"Liverpool"},{"_id":"5ce15d26a89ea100045373b1","country":"NZ","city":"Auckland"},{"_id":"5ce194f96ab31f000462d2ae","country":"BR","city":"Goiânia"},{"_id":"5ce19a806ab31f000462d2b9","country":"HK","city":"Hong Kong"},{"_id":"5d4474fb3eb2c00004a7ff7d","country":"US","city":"Greenfield"},{"_id":"5d4479523eb2c00004a7ff87","country":"UA","city":"Odesa"},{"_id":"5d447d2c3eb2c00004a7ff92","country":"BR","city":"Santa Maria"},{"_id":"5d4481e03eb2c00004a7ff98","country":"US","city":"Ringwood"},{"_id":"5d4483e63eb2c00004a7ff9e","country":"RO","city":"Bucharest"},{"_id":"5d44891c3eb2c00004a7ffab","country":"AU","city":"Perth"},{"_id":"5d448a903eb2c00004a7ffb0","country":"IN","city":"Pune"},{"_id":"6093d09bcfb2e70004ba66d9","country":"EG","city":"Cairo"},{"_id":"6093d441cfb2e70004ba66e4","country":"US","city":"Syracuse"},{"_id":"6093d68bcfb2e70004ba66ed","country":"BE","city":"Brussels"},{"_id":"6093d995cfb2e70004ba66f8","country":"CO","city":"Cali"},{"_id":"6093da74cfb2e70004ba66fb","country":"US","city":"Sothbury"},{"_id":"6093e053cfb2e70004ba6701","country":"CA","city":"Ottawa "},{"_id":"6093e2aecfb2e70004ba6709","country":"DE","city":"Weimar"},{"_id":"6093e332cfb2e70004ba670b","country":"US","city":"Culver City"},{"_id":"6093e56ecfb2e70004ba6712","country":"IE","city":"Kilkenny"},{"_id":"6093e628cfb2e70004ba6715","country":"PH","city":"Manila"},{"_id":"6093ec42cfb2e70004ba6723","country":"RU","city":"Moscow"},{"_id":"6093ed90cfb2e70004ba6727","country":"US","city":"Indianapolis"},{"_id":"6093ef09cfb2e70004ba672b","country":"CZ","city":"Prague"},{"_id":"6093f040cfb2e70004ba672f","country":"FR","city":"Rennes"},{"_id":"6093f1d0cfb2e70004ba6734","country":"US","city":"Arlington"},{"_id":"6094071a02b1150004ab310e","country":"UK","city":"Cardiff"},{"_id":"6094079702b1150004ab3111","country":"US","city":"Paterson"},{"_id":"6094085902b1150004ab3114","country":"US","city":"Appleton"},{"_id":"609408a102b1150004ab3116","country":"NL","city":"Enschede"},{"_id":"60940c5f02b1150004ab3122","country":"ID","city":"Canggu"},{"_id":"60940cef02b1150004ab3124","country":"TW","city":"Taipei"},{"_id":"6094105502b1150004ab3127","country":"PL","city":"Warsaw"},{"_id":"6095047d37330e00042cc58d","country":"US","city":"Redwood City"},{"_id":"609506c637330e00042cc595","country":"US","city":"Nashville"},{"_id":"60950dde37330e00042cc5a0","country":"US","city":"Buffalo"},{"_id":"609526a1791639000424cdfe","country":"ZA","city":"Johannesburg"},{"_id":"609528c7791639000424ce06","country":"IT","city":"Vicenza"},{"_id":"60952aa7791639000424ce0d","country":"US","city":"Las Vegas"},{"_id":"60952afb791639000424ce0f","country":"IN","city":"Vizag"},{"_id":"60952b4e791639000424ce11","country":"IN","city":"Gandhidham"},{"_id":"609534ea791639000424ce1e","country":"CA","city":"Winnipeg"},{"_id":"60953559791639000424ce20","country":"FR","city":"Nantes"},{"_id":"609538a6791639000424ce2b","country":"BR","city":"Blumenau"},{"_id":"60953af2791639000424ce32","country":"UY","city":"Montevideo"},{"_id":"60953c3c791639000424ce38","country":"IE","city":"Tipperary"},{"_id":"60953cec791639000424ce3a","country":"NL","city":"Tilburg"},{"_id":"60954a3f4b119f0004153b77","country":"US","city":"Hayward"},{"_id":"60954b5f4b119f0004153b7c","country":"US","city":"Vermont"},{"_id":"60954d9e4b119f0004153b85","country":"US","city":"Spring"},{"_id":"609915c2239b7e0004e37ccf","country":"US","city":"Bloomington"},{"_id":"60991976239b7e0004e37cdd","country":"US","city":"Union City"},{"_id":"6099295ebcf8fc0004f21185","country":"IN","city":"Bangalore"},{"_id":"609929e0bcf8fc0004f21187","country":"NL","city":"Rotterdam"},{"_id":"60992a47bcf8fc0004f21189","country":"AR","city":"Neuquén"},{"_id":"60993a87bcf8fc0004f21195","country":"IN","city":"Delhi"},{"_id":"60993cadbcf8fc0004f2119e","country":"FR","city":"Montpellier"},{"_id":"609941e8bcf8fc0004f211ab","country":"UK","city":"Peterhead"},{"_id":"60994318bcf8fc0004f211b0","country":"UK","city":"Aberdeen"},{"_id":"60994701bcf8fc0004f211b6","country":"US","city":"Grand Rapids"},{"_id":"609949b7bcf8fc0004f211c3","country":"PE","city":"Lima"},{"_id":"6099989d05f214000485c259","country":"IL","city":"Rehovot"},{"_id":"60999a0b05f214000485c25f","country":"US","city":"Hudson"},{"_id":"60999e3605f214000485c269","country":"US","city":"Santa Fe"},{"_id":"60999f7305f214000485c26e","country":"IT","city":"Florence"},{"_id":"6099a0e005f214000485c274","country":"PL","city":"Gdynia"},{"_id":"6099a1df05f214000485c279","country":"US","city":"Rockville"},{"_id":"60e48200bb06ec000494e81e","country":"UK","city":"Cheltenham"},{"_id":"60e584e6f0d7790004bf0849","country":"US","city":"San Carlos"},{"_id":"60e58610f0d7790004bf084f","country":"US","city":"Saint Paul"},{"_id":"60e58669f0d7790004bf0851","country":"ES","city":"Sevilla"},{"_id":"60e5af0d02077100044f1b13","country":"BG","city":"Sofia"},{"_id":"6103ec0733f1e50004491742","country":"UK","city":"Shrewsbury"},{"_id":"6103ec5833f1e50004491743","country":"BE","city":"Oud-Turnhout"},{"_id":"6103ece533f1e50004491747","country":"IN","city":"Tamil Nadu"},{"_id":"6103edab33f1e5000449174a","country":"UK","city":"Dundee"},{"_id":"61979c171c0fdc000412ffb1","country":"GR","city":"Thessaloniki"},{"_id":"61979cc01c0fdc000412ffb4","country":"US","city":"Las Cruces"},{"_id":"61979d4d1c0fdc000412ffb6","country":"US","city":"Ventura"},{"_id":"61979ecd1c0fdc000412ffbb","country":"US","city":"Chico"},{"_id":"61979f291c0fdc000412ffbd","country":"US","city":"Carmel"},{"_id":"6197a0551c0fdc000412ffc2","country":"UK","city":"Hebden Bridge"},{"_id":"6197a2911c0fdc000412ffcb","country":"SE","city":"Uppsala"},{"_id":"6197a3221c0fdc000412ffcd","country":"PL","city":"Lódz"},{"_id":"6197a4231c0fdc000412ffcf","country":"EE","city":"Tallinn"},{"_id":"6197a55e1c0fdc000412ffd3","country":"FR","city":"Châtillon sur Indre"},{"_id":"6197a75f1c0fdc000412ffd9","country":"UK","city":"Leicester"},{"_id":"6197a88a1c0fdc000412ffde","country":"US","city":"Carlin"},{"_id":"6197ab761c0fdc000412ffeb","country":"US","city":"Reidsville"},{"_id":"62261c44d43815000414d008","country":"MX","city":"Puebla"},{"_id":"62261d7ad43815000414d00c","country":"UK","city":"Cornwall"},{"_id":"62261dd4d43815000414d00e","country":"PK","city":"Karachi"},{"_id":"62261ee9d43815000414d012","country":"BR","city":"Porto Alegre"},{"_id":"62261f16d43815000414d014","country":"UK","city":"York"},{"_id":"6226204dd43815000414d018","country":"UK","city":"Plymouth"},{"_id":"62262122d43815000414d01b","country":"US","city":"Durham"},{"_id":"62262278d43815000414d020","country":"US","city":"Northampton"},{"_id":"6226255dd43815000414d026","country":"IN","city":"Barnala"},{"_id":"62262600d43815000414d02a","country":"US","city":"Tampa"},{"_id":"6226263cd43815000414d02c","country":"BR","city":"Joinville"},{"_id":"62262706d43815000414d02f","country":"US","city":"Tempe"},{"_id":"6226275bd43815000414d031","country":"DO","city":"Santo Domingo"},{"_id":"622627efd43815000414d034","country":"UA","city":"Mariupol"},{"_id":"62262867d43815000414d036","country":"PH","city":"Quezon City"},{"_id":"62262958d43815000414d03b","country":"AU","city":"Castlemaine"},{"_id":"622629b7d43815000414d03d","country":"UK","city":"Saxmundham"},{"_id":"62262b1ad43815000414d043","country":"US","city":"Mission"},{"_id":"62262b50d43815000414d045","country":"JP","city":"Kyoto"},{"_id":"62262bc9d43815000414d048","country":"VE","city":"Caracas"},{"_id":"62262c0fd43815000414d04a","country":"US","city":"Long Beach"},{"_id":"62262cb9d43815000414d04e","country":"US","city":"Hurleyville"},{"_id":"62262d24d43815000414d050","country":"ID","city":"Ubud"},{"_id":"6373919cc414a9000e1da9d5","country":"FR","city":"Arles"},{"_id":"6373921cc414a9000e1da9d7","country":"LB","city":"Beirut"},{"_id":"6373951ac414a9000e1da9df","country":"BR","city":"Juiz de Fora"},{"_id":"63739772c414a9000e1da9e6","country":"NL","city":"Delft"},{"_id":"6373989dc414a9000e1da9e9","country":"EG","city":"Obour"},{"_id":"63739ae6c414a9000e1da9f0","country":"AR","city":"Mar del Plata"},{"_id":"63739bcac414a9000e1da9f3","country":"BR","city":"Salvador"},{"_id":"6373a060c414a9000e1da9fc","country":"US","city":"Surprise"},{"_id":"6373a585c414a9000e1daa04","country":"CA","city":"Edmonton"},{"_id":"6373a67fc414a9000e1daa08","country":"BH","city":"Manama"},{"_id":"6373aa50c414a9000e1daa0e","country":"GE","city":"Tbilisi"},{"_id":"6373aac3c414a9000e1daa10","country":"CA","city":"Chase"},{"_id":"6373adeec414a9000e1daa17","country":"DE","city":"Hamburg"},{"_id":"6373b08bc414a9000e1daa1f","country":"US","city":"Gunnison"},{"_id":"6373b179c414a9000e1daa23","country":"US","city":"Missoula"},{"_id":"6373b88fc414a9000e1daa39","country":"FR","city":"Guadeloupe"},{"_id":"6373b9f9c414a9000e1daa3c","country":"TW","city":"Taichung"},{"_id":"6373bb68c414a9000e1daa43","country":"IN","city":"Bengaluru"},{"_id":"649d332f224147000cc24635","country":"ES","city":"Zaragoza"},{"_id":"649d33da224147000cc24638","country":"UK","city":"Dartford"},{"_id":"649d3522224147000cc2463c","country":"IN","city":"Mysuru"},{"_id":"649d3787224147000cc24646","country":"US","city":"West Covina"},{"_id":"649d380e224147000cc24648","country":"NL","city":"Blaricum"},{"_id":"649d38ab224147000cc2464b","country":"SE","city":"Karlskrona"},{"_id":"649d3b3e224147000cc24654","country":"ES","city":"Alaró"},{"_id":"649d3d76224147000cc2465c","country":"US","city":"Carlsbad"},{"_id":"649d3e40224147000cc2465f","country":"US","city":"Pittsburgh"},{"_id":"649d4092224147000cc24665","country":"UK","city":"Birmingham "},{"_id":"649d4291224147000cc2466d","country":"US","city":"Lafayette"},{"_id":"649d42f1224147000cc2466f","country":"DE","city":"Potsdam"},{"_id":"649d54a0224147000cc24673","country":"US","city":"Carrboro"},{"_id":"649d54f8224147000cc24675","country":"UK","city":"Bournemouth"},{"_id":"649d5682224147000cc2467b","country":"US","city":"Raleigh"},{"_id":"649d5799224147000cc2467f","country":"AT","city":"Graz"},{"_id":"649dc2ac224147000cc24690","country":"US","city":"Cumming"},{"_id":"649dc3d6224147000cc24694","country":"US","city":"East Orange"},{"_id":"649dc4d8224147000cc24698","country":"CA","city":"Aurora"},{"_id":"649dc531224147000cc2469a","country":"NL","city":"Groningen"},{"_id":"649dc5de224147000cc2469d","country":"US","city":"Victorville"},{"_id":"649dc6f7224147000cc246a1","country":"PH","city":"Naga City"},{"_id":"649dc82e224147000cc246a4","country":"US","city":"Gainesville"},{"_id":"654c0f8c456850000f98d63f","country":"AE","city":"Dubai"},{"_id":"654c0fdb456850000f98d641","country":"UK","city":"Brigg"},{"_id":"654c136c456850000f98d643","country":"FR","city":"Guéret"},{"_id":"654c15ca456850000f98d64c","country":"LV","city":"Riga"},{"_id":"654c1694456850000f98d64f","country":"US","city":"Newnan"},{"_id":"654c170e456850000f98d651","country":"UK","city":"Southampton"},{"_id":"654c17bf456850000f98d654","country":"US","city":"Wyandotte"},{"_id":"654c2517456850000f98d656","country":"US","city":"Irvine"},{"_id":"654c286f456850000f98d660","country":"FI","city":"Tampere"},{"_id":"654c2ac7456850000f98d66a","country":"UK","city":"Worcester"},{"_id":"654c2ce1456850000f98d672","country":"US","city":"Charleston"},{"_id":"67d370d261d2d5000fe710c1","country":"SE","city":"Jönköping"},{"_id":"67d373b061d2d5000fe710cb","country":"PA","city":"Valle de Anton"},{"_id":"67d3745f61d2d5000fe710ce","country":"NL","city":"Hague"},{"_id":"67d37c5561d2d5000fe710e9","country":"MY","city":"Kuala Lumpur"},{"_id":"67d37fd661d2d5000fe710f5","country":"US","city":"Orange Park"},{"_id":"67d3800161d2d5000fe710f6","country":"KZ","city":"Almaty"},{"_id":"67d3808361d2d5000fe710f9","country":"BA","city":"Saravejo"},{"_id":"67d44d4261d2d5000fe71102","country":"UK","city":"Tunbridge Wells"},{"_id":"67d44fec61d2d5000fe7110c","country":"FR","city":"Grenoble"},{"_id":"67d4514561d2d5000fe71110","country":"US","city":"Stafford"},{"_id":"67d4526661d2d5000fe71114","country":"UK","city":"East Grinstead"},{"_id":"67d45a2e61d2d5000fe7111d","country":"FI","city":"Helsinki"},{"_id":"67d45c4161d2d5000fe71127","country":"US","city":"Menlo Park"},{"_id":"67d45dfa61d2d5000fe7112f","country":"IN","city":"Kochi"}]}